{
    "$schema": "https://raw.githubusercontent.com/microsoft/vcpkg-tool/main/docs/vcpkg-configuration.schema.json",
    "default-registry": {
      "kind": "git",
      "repository": "https://github.com/microsoft/vcpkg",
      "baseline": "e140b1fde236eb682b0d47f905e65008a191800f"
    },
    "registries": [
      {
        "kind": "git",
        "repository": "https://github.com/Windscribe/ws-vcpkg-registry",
        "baseline": "713c97e1e07887c7f0cfe202962c3e9f233af06c",
        "packages": [
          "7zip",
          "boost-context",
          "boost-process",
          "c-ares",
          "ctrld",
          "curl",
          "lz4",
          "lzo",
          "miniaudio",
          "openvpn",
          "openssl",
          "qtbase",
          "qtimageformats",
          "qtsvg",
          "qttools",
          "qtwayland",
          "scapix",
          "scapix-bin",
          "skyr-url",
          "spdlog",
          "tap-windows6-driver"
        ]
      }
    ]
}
